kedro_dagster/__init__.py
kedro_dagster/catalog.py
kedro_dagster/cli.py
kedro_dagster/dagster.py
kedro_dagster/kedro.py
kedro_dagster/logging.py
kedro_dagster/nodes.py
kedro_dagster/pipelines.py
kedro_dagster/translator.py
kedro_dagster/utils.py
kedro_dagster/config/__init__.py
kedro_dagster/config/automation.py
kedro_dagster/config/execution.py
kedro_dagster/config/job.py
kedro_dagster/config/kedro_dagster.py
kedro_dagster/config/logging.py
kedro_dagster/datasets/__init__.py
kedro_dagster/datasets/nothing_dataset.py
kedro_dagster/datasets/partitioned_dataset.py
kedro_dagster/templates/dagster.yml
kedro_dagster/templates/definitions.py
kedro_dagster/templates/dg.toml
kedro_dagster-0.5.2.dist-info/METADATA
kedro_dagster-0.5.2.dist-info/WHEEL
kedro_dagster-0.5.2.dist-info/entry_points.txt
kedro_dagster-0.5.2.dist-info/licenses/LICENSE.md
kedro_dagster-0.5.2.dist-info/RECORD
