Metadata-Version: 2.4
Name: kedro-dagster
Version: 0.5.2
Summary: Kedro-Dagster makes it easy to deploy Kedro projects to Dagster
Project-URL: source_archive, https://github.com/gtauzin/kedro-dagster/archive/927ebbf344c015545a0f13c9b439f50496981499.zip
Author-email: Guillaume Tauzin <gtauzin.github@pm.me>
Maintainer-email: Guillaume Tauzin <gtauzin.github@pm.me>
License-Expression: Apache-2.0
License-File: LICENSE.md
Classifier: Operating System :: OS Independent
Classifier: Programming Language :: Python
Classifier: Programming Language :: Python :: 3 :: Only
Classifier: Programming Language :: Python :: 3.10
Classifier: Programming Language :: Python :: 3.11
Classifier: Programming Language :: Python :: 3.12
Classifier: Programming Language :: Python :: 3.13
Requires-Python: <3.14,>=3.10
Requires-Dist: dagster-dg-cli
Requires-Dist: dagster-webserver
Requires-Dist: dagster<2.0,>=1.10
Requires-Dist: kedro-datasets
Requires-Dist: kedro<2.0,>=0.19
Requires-Dist: pydantic<3.0.0,>=1.0.0
Provides-Extra: mlflow
Requires-Dist: dagster-mlflow; extra == 'mlflow'
Requires-Dist: kedro-mlflow>=0.13; extra == 'mlflow'
Requires-Dist: mlflow>=2.20; extra == 'mlflow'
